infuzu/__init__.py
infuzu/base.py
infuzu/constant_access.py
infuzu/constants.py
infuzu/access/__init__.py
infuzu/access/instance_access_profile.py
infuzu/access/object_access_profile.py
infuzu/access/user_access_profile.py
infuzu/authentication/__init__.py
infuzu/authentication/authenticate.py
infuzu/authentication/base.py
infuzu/authentication/requests.py
infuzu/authentication/shortcuts.py
infuzu/clockwise/__init__.py
infuzu/clockwise/errors.py
infuzu/clockwise/assignments/__init__.py
infuzu/clockwise/assignments/complete_assignment.py
infuzu/clockwise/assignments/retrieve_assignment.py
infuzu/clockwise/rules/__init__.py
infuzu/clockwise/rules/base.py
infuzu/clockwise/rules/calls.py
infuzu/clockwise/rules/execution_log.py
infuzu/cogitobot/__init__.py
infuzu/cogitobot/document_version.py
infuzu/errors/__init__.py
infuzu/errors/base.py
infuzu/errors/subscription_overviews.py
infuzu/errors/subscription_plans.py
infuzu/errors/subscriptions.py
infuzu/errors/user_and_subscription.py
infuzu/errors/user_subscriptions.py
infuzu/errors/users.py
infuzu/http_requests/__init__.py
infuzu/http_requests/base.py
infuzu/subscriptions/__init__.py
infuzu/subscriptions/overview.py
infuzu/subscriptions/subscription.py
infuzu/subscriptions/subscription_plan.py
infuzu/subscriptions/user_subscription.py
infuzu/users/__init__.py
infuzu/users/marketing_preference.py
infuzu/users/user.py
infuzu/utils/__init__.py
infuzu/utils/caching.py
infuzu/utils/encryption.py
infuzu/utils/random.py
infuzu/utils/signatures.py
infuzu/utils/api_calls/__init__.py
infuzu/utils/api_calls/base.py
infuzu/utils/api_calls/serialize.py
infuzu/utils/django/__init__.py
infuzu/utils/django/decorators.py
infuzu/utils/django/middleware.py
infuzu/utils/enums/__init__.py
infuzu/utils/enums/api_calls.py
infuzu/utils/enums/base.py
infuzu/utils/enums/checks.py
infuzu_python_sdk-0.87.2.dist-info/LICENSE.md
infuzu_python_sdk-0.87.2.dist-info/METADATA
infuzu_python_sdk-0.87.2.dist-info/WHEEL
infuzu_python_sdk-0.87.2.dist-info/top_level.txt
infuzu_python_sdk-0.87.2.dist-info/RECORD
