Metadata-Version: 2.1
Name: infuzu-python-sdk
Version: 0.87.2
Summary: This SDK provides a set of tools to manage assignments from Clockwise. Primarily, it allows you to fetch, represent, and mark assignments as complete.
Home-page: https://github.com/Infuzu/InfuzuPythonSDK
Author: Infuzu
Author-email: help@infuzu.com
Classifier: Programming Language :: Python :: 3
Classifier: License :: OSI Approved :: MIT License
License-File: LICENSE.md
